pyinternals/__init__.py
pyinternals/cpy_layouts.py
pyinternals/visualizer.py
pyinternals-0.1.3.dist-info/METADATA
pyinternals-0.1.3.dist-info/WHEEL
pyinternals-0.1.3.dist-info/top_level.txt
pyinternals-0.1.3.dist-info/RECORD
