Metadata-Version: 2.4
Name: pyinternals
Version: 0.1.3
Summary: A Python object layout visualizer using CPython internals
Home-page: https://github.com/yourusername/cpy_layouts
Author: Mohamed Desouky
Author-email: Mohamed Desouky <mohamed.d180@gmail.com>
License-Expression: MIT
Project-URL: Homepage, https://github.com/mohamed-180/pyinternals
Keywords: cpython,visualizer,memory,introspection
Requires-Python: >=3.7
Dynamic: author
Dynamic: home-page
Dynamic: requires-python
